pyconversor/__init__.py
pyconversor/pyconvert.py
pyconversor/modules/Node.py
pyconversor/modules/Tree.py
pyconversor/modules/__init__.py
pyconversor-0.0.1.dist-info/METADATA
pyconversor-0.0.1.dist-info/WHEEL
pyconversor-0.0.1.dist-info/licenses/LICENSE
pyconversor-0.0.1.dist-info/RECORD
