Metadata-Version: 2.1
Name: pyconversor
Version: 0.0.1
Summary: pyconversor is a lib developed with the aim of unifying all the conversion tools a dev might need during development in one place.
Author-email: Matheus Henrique Ptasinski Rosa <matheushpr9@gmail.com>
License-File: LICENSE
Classifier: License :: OSI Approved :: MIT License
Classifier: Operating System :: OS Independent
Classifier: Programming Language :: Python :: 3
